[{"__symbolic":"module","version":4,"metadata":{},"exports":[{"from":"./framework-library.service","export":["FrameworkLibraryService"]},{"from":"./no-framework/no.framework","export":["NoFramework"]},{"from":"./no-framework/no-framework.module","export":["NoFrameworkModule"]},{"from":"./material-design-framework/material-design.framework","export":["MaterialDesignFramework"]},{"from":"./material-design-framework/material-design-framework.module","export":["MaterialDesignFrameworkModule"]},{"from":"./bootstrap-3-framework/bootstrap-3.framework","export":["Bootstrap3Framework"]},{"from":"./bootstrap-3-framework/bootstrap-3-framework.module","export":["Bootstrap3FrameworkModule"]},{"from":"./bootstrap-4-framework/bootstrap-4.framework","export":["Bootstrap4Framework"]},{"from":"./bootstrap-4-framework/bootstrap-4-framework.module","export":["Bootstrap4FrameworkModule"]}]}]